qsAPI/__init__.py
qsAPI/__main__.py
qsAPI/_controller.py
qsAPI/_interfaces.py
qsAPI/qsAPI.py
qsAPI-2.2.0.dist-info/LICENSE
qsAPI-2.2.0.dist-info/METADATA
qsAPI-2.2.0.dist-info/WHEEL
qsAPI-2.2.0.dist-info/entry_points.txt
qsAPI-2.2.0.dist-info/top_level.txt
qsAPI-2.2.0.dist-info/RECORD
