Metadata-Version: 2.1
Name: qsAPI
Version: 2.2.0
Summary: qsAPI - a client for Qlik Sense QPS and QRS interfaces
Home-page: https://github.com/rafael-sanz/qsAPI
Author: Rafael Sanz
Author-email: rafael.sanz@selab.es
License: UNKNOWN
Platform: UNKNOWN
Classifier: Programming Language :: Python :: 3
Classifier: License :: OSI Approved :: MIT License
Classifier: Operating System :: OS Independent
Requires-Dist: requests
Provides-Extra: ntlm
Requires-Dist: requests-ntlm ; extra == 'ntlm'
